lance/__init__.py
lance/generators/__init__.py
lance/generators/java/__init__.py
lance/generators/java/annotations.py
lance/generators/java/attribute.py
lance/generators/java/constructor.py
lance/generators/java/enum.py
lance/generators/java/helper.py
lance/generators/java/interface.py
lance/generators/java/klass.py
lance/generators/java/method.py
lance/generators/java/schema_reader.py
lance/generators/java/typs.py
lance/generators/java/test/__init__.py
lance/generators/java/test/test_annotation.py
lance/generators/java/test/test_attribute.py
lance/generators/java/test/test_class.py
lance/generators/java/test/test_common.py
lance/generators/java/test/test_enum.py
lance/generators/java/test/test_interface.py
lance/generators/java/test/test_method.py
lance/generators/java/test/test_schema_reader.py
lance/generators/java/test/test_types.py
lance-1.2.1.dist-info/LICENSE
lance-1.2.1.dist-info/METADATA
lance-1.2.1.dist-info/WHEEL
lance-1.2.1.dist-info/top_level.txt
lance-1.2.1.dist-info/RECORD
