Metadata-Version: 2.1
Name: lance
Version: 1.2.1
Summary: A helper package to generate code from declarative json
Home-page: https://github.com/susamn/lance
Author: Supratim Samanta
Author-email: tech.supratim.samanta@gmail.com
License: UNKNOWN
Platform: UNKNOWN
Classifier: Programming Language :: Python :: 3
Classifier: License :: OSI Approved :: MIT License
Classifier: Operating System :: OS Independent
Requires-Python: >=3.6
